pyina/__info__.py
pyina/__init__.py
pyina/__main__.py
pyina/ez_map.py
pyina/launchers.py
pyina/mappers.py
pyina/mpi.py
pyina/mpi_pool.py
pyina/mpi_scatter.py
pyina/schedulers.py
pyina/tools.py
pyina/tests/__init__.py
pyina/tests/__main__.py
pyina/tests/test_ezmap.py
pyina/tests/test_map.py
pyina/tests/test_pool.py
pyina/tests/test_simple.py
pyina/tests/test_star.py
pyina/tests/test_with.py
pyina-0.3.2.data/scripts/ezpool
pyina-0.3.2.data/scripts/ezscatter
pyina-0.3.2.data/scripts/mpi_world
pyina-0.3.2.dist-info/LICENSE
pyina-0.3.2.dist-info/METADATA
pyina-0.3.2.dist-info/WHEEL
pyina-0.3.2.dist-info/top_level.txt
pyina-0.3.2.dist-info/RECORD
